[{"PlaceString":0,"DateString":"1-1-1-1","ConflictForm":"Battle","Title":"1","ZFriendsString":"1,12","ZEnemysString":"46,47","FfriendsString":"","FenemysString":"1,12"},{"PlaceString":0,"DateString":"1-1-1-2","ConflictForm":"Battle","Title":"2","ZFriendsString":"1,12","ZEnemysString":"52,2*89","FfriendsString":"","FenemysString":"1,12"},{"PlaceString":0,"DateString":"1-1-1-3","ConflictForm":"Battle","Title":"3","ZFriendsString":"1,9","ZEnemysString":"4*90","FfriendsString":"","FenemysString":"1,9"},{"PlaceString":0,"DateString":"1-1-1-4","ConflictForm":"Battle","Title":"4","ZFriendsString":"1,9","ZEnemysString":"60,61","FfriendsString":"","FenemysString":"1,9"},{"PlaceString":0,"DateString":"1-1-1-5","ConflictForm":"Battle","Title":"5","ZFriendsString":"41,42,43,44","ZEnemysString":"21,22,23,47","FfriendsString":"21,22,23,47","FenemysString":"41,42,43,44"},{"PlaceString":0,"DateString":"1-1-1-6","ConflictForm":"Battle","Title":"6","ZFriendsString":"1","ZEnemysString":"7*89","FfriendsString":"","FenemysString":1},{"PlaceString":0,"DateString":"1-1-1-7","ConflictForm":"WeiQi","Title":"7","ZFriendsString":"","ZEnemysString":"","FfriendsString":"","FenemysString":""},{"PlaceString":0,"DateString":"1-1-1-8","ConflictForm":"Battle","Title":"8","ZFriendsString":35,"ZEnemysString":10,"FfriendsString":10,"FenemysString":"31,32,33,34,35"},{"PlaceString":0,"DateString":"1-1-1-9","ConflictForm":"Battle","Title":"9","ZFriendsString":"24,7","ZEnemysString":"55,56","FfriendsString":"","FenemysString":"24,7"},{"PlaceString":0,"DateString":"1-1-1-10","ConflictForm":"ThanLiquor","Title":"10","ZFriendsString":"","ZEnemysString":2,"FfriendsString":"","FenemysString":1},{"PlaceString":0,"DateString":"1-1-1-11","ConflictForm":"Battle","Title":"11","ZFriendsString":2,"ZEnemysString":"36,37,38,39,40","FfriendsString":"","FenemysString":2},{"PlaceString":0,"DateString":"1-1-1-12","ConflictForm":"Battle","Title":"12","ZFriendsString":1,"ZEnemysString":"59,7*91","FfriendsString":"","FenemysString":1},{"PlaceString":0,"DateString":"1-1-1-13","ConflictForm":"Battle","Title":"13","ZFriendsString":"2,5","ZEnemysString":28,"FfriendsString":28,"FenemysString":"2,5"},{"PlaceString":0,"DateString":"1-1-1-14","ConflictForm":"Battle","Title":"14","ZFriendsString":2,"ZEnemysString":"48,49,51,53,54,30,26,27,36,37,38,39,40","FfriendsString":"","FenemysString":"2"},{"PlaceString":0,"DateString":"1-1-1-15","ConflictForm":"Battle","Title":"15","ZFriendsString":8,"ZEnemysString":14,"FfriendsString":14,"FenemysString":8},{"PlaceString":0,"DateString":"1-1-1-16","ConflictForm":"Battle","Title":"16","ZFriendsString":4,"ZEnemysString":"4*92","FfriendsString":"","FenemysString":2},{"PlaceString":0,"DateString":"1-1-1-17","ConflictForm":"Battle","Title":"17","ZFriendsString":2,"ZEnemysString":"12*93","FfriendsString":"","FenemysString":2},{"PlaceString":0,"DateString":"1-1-1-18","ConflictForm":"Battle","Title":"18","ZFriendsString":29,"ZEnemysString":13,"FfriendsString":"","FenemysString":29},{"PlaceString":0,"DateString":"1-1-1-19","ConflictForm":"WeiQi","Title":"19","ZFriendsString":"","ZEnemysString":"","FfriendsString":"","FenemysString":""},{"PlaceString":0,"DateString":"1-1-1-20","ConflictForm":"Battle","Title":"20","ZFriendsString":6,"ZEnemysString":"45,58,63,64","FfriendsString":"","FenemysString":6},{"PlaceString":0,"DateString":"1-1-1-21","ConflictForm":"Battle","Title":"21","ZFriendsString":"3,19","ZEnemysString":15,"FfriendsString":15,"FenemysString":"3,19"},{"PlaceString":0,"DateString":"1-1-1-22","ConflictForm":"Battle","Title":"22","ZFriendsString":"3,19","ZEnemysString":15,"FfriendsString":15,"FenemysString":"3,19"},{"PlaceString":0,"DateString":"1-1-1-23","ConflictForm":"Battle","Title":"23","ZFriendsString":3,"ZEnemysString":"57,62,6","FfriendsString":"","FenemysString":3},{"PlaceString":0,"DateString":"1-1-1-24","ConflictForm":"Battle","Title":"24","ZFriendsString":3,"ZEnemysString":10,"FfriendsString":10,"FenemysString":3},{"PlaceString":0,"DateString":"1-1-1-25","ConflictForm":"Battle","Title":"25","ZFriendsString":28,"ZEnemysString":11,"FfriendsString":11,"FenemysString":28},{"PlaceString":0,"DateString":"1-1-1-26","ConflictForm":"Battle","Title":"26","ZFriendsString":"1,2,3","ZEnemysString":"6,11,13","FfriendsString":"6,11,13","FenemysString":"1,2,3"},{"PlaceString":0,"DateString":"1-1-1-27","ConflictForm":"Battle","Title":"27","ZFriendsString":2,"ZEnemysString":20,"FfriendsString":"","FenemysString":2},{"PlaceString":0,"DateString":"1-1-1-28","ConflictForm":"Battle","Title":"28","ZFriendsString":1,"ZEnemysString":6,"FfriendsString":6,"FenemysString":1},{"PlaceString":0,"DateString":"1-1-1-29","ConflictForm":"Battle","Title":"29","ZFriendsString":"","ZEnemysString":"1,2,3","FfriendsString":"","FenemysString":"6,10,14"}]